resspect/__init__.py
resspect/_version.py
resspect/base_configuration.py
resspect/batch_functions.py
resspect/bazin.py
resspect/build_plasticc_canonical.py
resspect/build_plasticc_metadata.py
resspect/build_snpcc_canonical.py
resspect/bump.py
resspect/classifiers.py
resspect/cosmo_metric_utils.py
resspect/database.py
resspect/exposure_time_calculator.py
resspect/feature_handling_utils.py
resspect/filter_sets.py
resspect/fit_lightcurves.py
resspect/learn_loop.py
resspect/lightcurves_utils.py
resspect/loop_configuration.py
resspect/metrics.py
resspect/plot_results.py
resspect/plugin_utils.py
resspect/query_budget_strategies.py
resspect/query_strategies.py
resspect/read_dash.py
resspect/readme.rst
resspect/salt3_utils.py
resspect/samples_utils.py
resspect/snana_fits_to_pd.py
resspect/time_domain_configuration.py
resspect/time_domain_loop.py
resspect/time_domain_plasticc.py
resspect/time_domain_snpcc.py
resspect/tom_client.py
resspect/update_stashes.py
resspect/feature_extractors/__init__.py
resspect/feature_extractors/bazin.py
resspect/feature_extractors/bump.py
resspect/feature_extractors/feature_extractor_utils.py
resspect/feature_extractors/light_curve.py
resspect/feature_extractors/malanchev.py
resspect/scripts/__init__.py
resspect/scripts/build_canonical.py
resspect/scripts/build_time_domain_plasticc.py
resspect/scripts/build_time_domain_snpcc.py
resspect/scripts/calculate_cosmology_metric.py
resspect/scripts/fetch_example_data.py
resspect/scripts/fit_dataset.py
resspect/scripts/make_metrics_plots.py
resspect/scripts/run_loop.py
resspect/scripts/run_time_domain.py
resspect/snanapipe/__init__.py
resspect/snanapipe/samplerun.py
resspect/snanapipe/snana_hook.py
resspect-0.2.dist-info/LICENSE
resspect-0.2.dist-info/METADATA
resspect-0.2.dist-info/WHEEL
resspect-0.2.dist-info/entry_points.txt
resspect-0.2.dist-info/top_level.txt
resspect-0.2.dist-info/RECORD
