Metadata-Version: 2.1
Name: resspect
Version: 0.2
Author-email: The RESSPECT team <contact@cosmostatistics-initiative.org>
License: MIT License
Project-URL: Homepage, https://lsst-resspect.readthedocs.io/en/latest/
Project-URL: Source, https://github.com/LSSTDESC/RESSPECT
Classifier: Development Status :: 4 - Beta
Classifier: License :: OSI Approved :: MIT License
Classifier: Intended Audience :: Developers
Classifier: Intended Audience :: Science/Research
Classifier: Operating System :: OS Independent
Classifier: Programming Language :: Python
Requires-Python: >=3.9
License-File: LICENSE
Requires-Dist: flask==2.3.2
Requires-Dist: astropy>=5.2.1
Requires-Dist: matplotlib>=3.7.0
Requires-Dist: numba
Requires-Dist: numpy>=1.24.2
Requires-Dist: pandas>=1.5.3
Requires-Dist: progressbar2>=4.2.0
Requires-Dist: scikit_learn>=1.2.1
Requires-Dist: scipy>=1.10.0
Requires-Dist: seaborn>=0.12.2
Requires-Dist: xgboost>=1.7.3
Requires-Dist: iminuit>=1.20.0
Requires-Dist: light_curve>=0.8.1
Requires-Dist: requests
Requires-Dist: pooch
Requires-Dist: platformdirs
Provides-Extra: dev
Requires-Dist: asv==0.6.4; extra == "dev"
Requires-Dist: jupyter; extra == "dev"
Requires-Dist: pre-commit; extra == "dev"
Requires-Dist: pytest; extra == "dev"
Requires-Dist: pytest-cov; extra == "dev"
